{"id": 5, "ts": "2022-11-27 00:35:12.312Z", "author": "mankings", "description": "Será que vai acordar?", "name": "Mankings adormece no dlc", "tags": ["comedy", "mistery"]}
{"id": 10, "ts": "2022-11-27 00:35:12.324Z", "author": "lucas", "description": "Roblox gameplay", "name": "Jogando muito feliz", "tags": ["casual", "gaming"]}
{"id": 13, "ts": "2022-11-27 00:35:12.330Z", "author": "feromonas", "description": "Indo para o Japão", "name": "Fui viajar!", "tags": ["spiceoflife", "vlog"]}
{"id": 11, "ts": "2022-11-27 00:35:12.326Z", "author": "marychannel", "description": "Mas que estala enorme", "name": "Uma noite no BE", "tags": ["spiceoflife", "vlog"]}
{"id": 1, "ts": "2022-11-27 00:35:12.300Z", "author": "tiagovski", "description": "Homenagem aos jogadores", "name": "Equipa de Fifa15", "tags": ["comedy", "gaming"]}
{"id": 8, "ts": "2022-11-27 00:35:12.320Z", "author": "jarvas", "description": "Retorno do Jarvas", "name": "Onde estive?", "tags": ["mistery", "oldschool"]}
{"id": 2, "ts": "2022-11-27 00:35:12.303Z", "author": "feromonas", "description": "Gameplay de Minecraft", "name": "Lenda da Redstone", "tags": ["gaming", "oldschool"]}
{"id": 4, "ts": "2022-11-27 00:35:12.308Z", "author": "pewdiepie", "description": "Be careful with them", "name": "Barrels", "tags": ["comedy", "mistery"]}
{"id": 7, "ts": "2022-11-27 00:35:12.317Z", "author": "ricfazeres", "description": "Muito picantes!", "name": "As novas pimentas do tio Ric", "tags": ["comedy", "spiceoflife"]}
{"id": 6, "ts": "2022-11-27 00:35:12.315Z", "author": "markiplier", "description": "Spooky Gameply", "name": "Five Nights at Freddys", "tags": ["gaming", "horror"]}
{"id": 9, "ts": "2022-11-27 00:35:12.322Z", "author": "marychannel", "description": "Ainda por cima açoriana", "name": "Vida de uma universitária", "tags": ["spiceoflife", "vlog"]}
{"id": 14, "ts": "2022-11-27 00:35:12.332Z", "author": "mankings", "description": "Tutorial in-depth", "name": "Vivendo com manquisse", "tags": ["mistery", "vlog"]}
{"id": 12, "ts": "2022-11-27 00:35:12.328Z", "author": "ricfazeres", "description": "Progresso na casa", "name": "Vlog da casa nova", "tags": ["spiceoflife", "vlog"]}
{"id": 3, "ts": "2022-11-27 00:35:12.305Z", "author": "venom", "description": "Tá ficando apertado!", "name": "Slither.io Gameplay", "tags": ["comedy", "gaming"]}